seven_segment_display/double_dabble.v
`timescale 1ns / 1ps
module double_dabble(
    input clk,
    input reset,
    input start,
    input[15:0] binary_in,
    output reg [3:0] bcd0,
    output reg [3:0] bcd1,
    output reg [3:0] bcd2,
    output reg [3:0] bcd3,
    output reg [3:0] bcd4,
    output reg busy,
    output reg done
);
    initial begin
        busy <= 0;
        done <= 0;
    end

    reg[3:0] temp = 0;
    reg[4:0] counter = 0;
    reg[35:0] scratch_space = 36'd0;
    wire test = scratch_space[19:16] >= 4'd5;

    always @(posedge clk or posedge reset) begin
        if (reset) begin
            scratch_space <= 0;
            busy <= 0;
            done <= 0;
            counter <= 0;
        end else if (clk) begin
            if (start && !busy) begin
                scratch_space <= {20'b0, binary_in};
                counter <= 0;
                busy <= 1;
                done <= 0;
            end else if (busy) begin
                // add 3 if any group is at least 5
                if (scratch_space[19:16] >= 4'd5) begin
                    temp = scratch_space[19:16] + 4'd3;
                    scratch_space[19:16] = temp;
                end
                if (scratch_space[23:20] >= 4'd5) begin
                    temp = scratch_space[23:20] + 4'd3;
                    scratch_space[23:20] = temp;
                end
                if (scratch_space[27:24] >= 4'd5) begin
                    temp = scratch_space[27:24] + 4'd3;
                    scratch_space[27:24] = temp;
                end
                if (scratch_space[31:28] >= 4'd5) begin
                    temp = scratch_space[31:28] + 4'd3;
                    scratch_space[31:28] = temp;
                end
                if (scratch_space[35:32] >= 4'd5) begin
                    temp = scratch_space[35:32] + 4'd3;
                    scratch_space[35:32] = temp;
                end
                
                scratch_space = scratch_space << 1;
                counter = counter + 1;

                if (counter == 5'd16) begin
                    // extract BCD bits
                    bcd0 <= scratch_space[19:16];
                    bcd1 <= scratch_space[23:20];
                    bcd2 <= scratch_space[27:24];
                    bcd3 <= scratch_space[31:28];
                    bcd4 <= scratch_space[35:32];

                    busy <= 0;
                    done <= 1;
                end
            end
        end
    end

endmodule

seven_segment_display/double_dabble_tb.v
`timescale 1ns / 100ps
module double_dabble_tb;
    reg[15:0] score = 16'd754;
    reg start, clk;
    wire[3:0] bcd0, bcd1, bcd2, bcd3, bcd4;
    wire busy, done;
    wire reset = 1'b0;

    initial begin
        start <= 0;
    end

    double_dabble binary_to_BCD(
        .clk(clk),
        .reset(reset),
        .start(start),
        .binary_in(score),
        .bcd0(bcd0),
        .bcd1(bcd1),
        .bcd2(bcd2),
        .bcd3(bcd3),
        .bcd4(bcd4),
        .busy(busy),
        .done(done)
    );

    // Start BCD conversion when score changes
    reg[15:0] last_score = 16'd0;
    always @(posedge clk) begin
        if (reset) begin
            start <= 1;
            last_score <= 0;
        end else if (score != last_score && !busy) begin
            start <= 1;
            last_score <= score;
        end else
            start <= 0;
    end

    initial begin
        clk = 0;
        #9000000;
        $finish;
    end

    always
        #50000 clk = ~clk;

    always @(clk) begin
        $display("BCD0:%d, BCD1:%d, BCD2:%d, BCD3:%d, BCD4:%d, busy:%b, done:%b, start:%b", bcd0, bcd1, bcd2, bcd3, bcd4, busy, done, start);
    end

    initial begin
        $dumpfile("double_dabble_tb.vcd");
        $dumpvars(0, double_dabble_tb);
    end
endmodule

seven_segment_display/double_dabble_tb.vcd
$date
	Wed Apr 23 11:43:46 2025
$end
$version
	Icarus Verilog
$end
$timescale
	1ps
$end
$scope module double_dabble_tb $end
$var wire 1 ! reset $end
$var wire 1 " done $end
$var wire 1 # busy $end
$var wire 4 $ bcd4 [3:0] $end
$var wire 4 % bcd3 [3:0] $end
$var wire 4 & bcd2 [3:0] $end
$var wire 4 ' bcd1 [3:0] $end
$var wire 4 ( bcd0 [3:0] $end
$var reg 1 ) clk $end
$var reg 16 * last_score [15:0] $end
$var reg 16 + score [15:0] $end
$var reg 1 , start $end
$scope module binary_to_BCD $end
$var wire 16 - binary_in [15:0] $end
$var wire 1 ) clk $end
$var wire 1 ! reset $end
$var wire 1 , start $end
$var wire 1 . test $end
$var reg 4 / bcd0 [3:0] $end
$var reg 4 0 bcd1 [3:0] $end
$var reg 4 1 bcd2 [3:0] $end
$var reg 4 2 bcd3 [3:0] $end
$var reg 4 3 bcd4 [3:0] $end
$var reg 1 # busy $end
$var reg 5 4 counter [4:0] $end
$var reg 1 " done $end
$var reg 36 5 scratch_space [35:0] $end
$var reg 4 6 temp [3:0] $end
$upscope $end
$upscope $end
$enddefinitions $end
$comment Show the parameter values. $end
$dumpall
$end
#0
$dumpvars
b0 6
b0 5
b0 4
bx 3
bx 2
bx 1
bx 0
bx /
0.
b1011110010 -
0,
b1011110010 +
b0 *
0)
bx (
bx '
bx &
bx %
bx $
0#
0"
0!
$end
#50000000
b1011110010 *
1,
1)
#100000000
0)
#150000000
1#
b1011110010 5
0,
1)
#200000000
0)
#250000000
b1 4
b10111100100 5
1)
#300000000
0)
#350000000
b10 4
b101111001000 5
1)
#400000000
0)
#450000000
b11 4
b1011110010000 5
1)
#500000000
0)
#550000000
b100 4
b10111100100000 5
1)
#600000000
0)
#650000000
b101 4
b101111001000000 5
1)
#700000000
0)
#750000000
b110 4
b1011110010000000 5
1)
#800000000
0)
#850000000
b111 4
b10111100100000000 5
1)
#900000000
0)
#950000000
b1000 4
b101111001000000000 5
1)
#1000000000
0)
#1050000000
1.
b1001 4
b1011110010000000000 5
1)
#1100000000
0)
#1150000000
0.
b1010 4
b100011100100000000000 5
b1000 6
1)
#1200000000
0)
#1250000000
b1011 4
b1000111001000000000000 5
1)
#1300000000
0)
#1350000000
1.
b1100 4
b10001110010000000000000 5
1)
#1400000000
0)
#1450000000
0.
b1101 4
b100101000100000000000000 5
b1010 6
1)
#1500000000
0)
#1550000000
1.
b1110 4
b1100010001000000000000000 5
b1100 6
1)
#1600000000
0)
#1650000000
b1111 4
b11011101110000000000000000 5
b1011 6
1)
#1700000000
0)
#1750000000
1"
0#
b0 $
b0 3
b0 %
b0 2
b111 &
b111 1
b101 '
b101 0
b100 (
b100 /
0.
b10000 4
b111010101000000000000000000 5
b1010 6
1)
