seven_segment_display/BCD_to_display.v
`timescale 1ns / 1ps
module BCD_to_display(
    input[3:0] BCD,
    output reg[6:0] segment
);

    always @(*) begin
        case (BCD)
            4'd0: segment = 7'b1000000;
            4'd1: segment = 7'b1111001;
            4'd2: segment = 7'b0100100;
            4'd3: segment = 7'b0110000;
            4'd4: segment = 7'b0011001;
            4'd5: segment = 7'b0010010;
            4'd6: segment = 7'b0000010;
            4'd7: segment = 7'b1111000;
            4'd8: segment = 7'b0000000;
            4'd9: segment = 7'b0010000;
            default: segment = 7'b0000000;
        endcase
    end
endmodule

seven_segment_display/double_dabble.v
`timescale 1ns / 1ps
module double_dabble(
    input clk,
    input reset,
    input start,
    input[15:0] binary_in,
    output reg [3:0] bcd0,
    output reg [3:0] bcd1,
    output reg [3:0] bcd2,
    output reg [3:0] bcd3,
    output reg [3:0] bcd4,
    output reg busy,
    output reg done
);
    initial begin
        busy <= 0;
        done <= 0;
    end

    reg[3:0] temp = 0;
    reg[4:0] counter = 0;
    reg[35:0] scratch_space = 36'd0;
    wire test = scratch_space[19:16] >= 4'd5;

    always @(posedge clk or posedge reset) begin
        if (reset) begin
            scratch_space <= 0;
            busy <= 0;
            done <= 0;
            counter <= 0;
        end else if (clk) begin
            if (start && !busy) begin
                scratch_space <= {20'b0, binary_in};
                counter <= 0;
                busy <= 1;
                done <= 0;
            end else if (busy) begin
                // add 3 if any group is at least 5
                if (scratch_space[19:16] >= 4'd5) begin
                    temp = scratch_space[19:16] + 4'd3;
                    scratch_space[19:16] = temp;
                end
                if (scratch_space[23:20] >= 4'd5) begin
                    temp = scratch_space[23:20] + 4'd3;
                    scratch_space[23:20] = temp;
                end
                if (scratch_space[27:24] >= 4'd5) begin
                    temp = scratch_space[27:24] + 4'd3;
                    scratch_space[27:24] = temp;
                end
                if (scratch_space[31:28] >= 4'd5) begin
                    temp = scratch_space[31:28] + 4'd3;
                    scratch_space[31:28] = temp;
                end
                if (scratch_space[35:32] >= 4'd5) begin
                    temp = scratch_space[35:32] + 4'd3;
                    scratch_space[35:32] = temp;
                end
                
                scratch_space = scratch_space << 1;
                counter = counter + 1;

                if (counter == 5'd16) begin
                    // extract BCD bits
                    bcd0 <= scratch_space[19:16];
                    bcd1 <= scratch_space[23:20];
                    bcd2 <= scratch_space[27:24];
                    bcd3 <= scratch_space[31:28];
                    bcd4 <= scratch_space[35:32];

                    busy <= 0;
                    done <= 1;
                end
            end
        end
    end

endmodule

seven_segment_display/seven_segment_display.v
`timescale 1ns / 1ps
module seven_segment_display(
    input clk,
    input reset,
    input[15:0] score,
    output reg[7:0] AN,
    output reg CA,
    output reg CB,
    output reg CC,
    output reg CD,
    output reg CE,
    output reg CF,
    output reg CG
);

    wire[3:0] bcd0, bcd1, bcd2, bcd3, bcd4;
    wire done, busy;
    reg start = 0;

    initial begin
        AN <= 0;
        CA <= 0;
        CB <= 0;
        CC <= 0;
        CD <= 0;
        CE <= 0;
        CF <= 0;
        CG <= 0;
    end

    // Convert binary score to BCD
    double_dabble binary_to_BCD(
        .clk(clk),
        .reset(reset),
        .start(start),
        .binary_in(score),
        .bcd0(bcd0),
        .bcd1(bcd1),
        .bcd2(bcd2),
        .bcd3(bcd3),
        .bcd4(bcd4),
        .busy(busy),
        .done(done)
    );

    // Get segment output
    wire[6:0] seg0, seg1, seg2, seg3, seg4;
    BCD_to_display bcd_0(.BCD(bcd0), .segment(seg0));
    BCD_to_display bcd_1(.BCD(bcd1), .segment(seg1));
    BCD_to_display bcd_2(.BCD(bcd2), .segment(seg2));
    BCD_to_display bcd_3(.BCD(bcd3), .segment(seg3));
    BCD_to_display bcd_4(.BCD(bcd4), .segment(seg4));

    // Start BCD conversion when score changes
    reg[15:0] last_score = 16'd0;
    always @(posedge clk) begin
        if (reset) begin
            start <= 1;
            last_score <= 0;
        end else if (score != last_score && !busy) begin
            start <= 1;
            last_score <= score;
        end else
            start <= 0;
    end

    // Display to LEDs
    reg[2:0] digit_on = 3'd0;
    reg[2:0] temp = 3'd0;
    always @(posedge clk) begin
        AN[0] <= ~(digit_on == 3'd0);
        AN[1] <= ~(digit_on == 3'd1);
        AN[2] <= ~(digit_on == 3'd2);
        AN[3] <= ~(digit_on == 3'd3);
        AN[4] <= ~(digit_on == 3'd4);
        AN[5] <= ~(digit_on == 3'd5);
        AN[6] <= ~(digit_on == 3'd6);
        AN[7] <= ~(digit_on == 3'd7);

        if (done) begin
            if (reset)
                digit_on <= 3'd0;
            else if (digit_on == 3'd0)
                {CG, CF, CE, CD, CC, CB, CA} <= seg0;
            else if (digit_on == 3'd1)
                {CG, CF, CE, CD, CC, CB, CA} <= seg1;
            else if (digit_on == 3'd2)
                {CG, CF, CE, CD, CC, CB, CA} <= seg2;
            else if (digit_on == 3'd3)
                {CG, CF, CE, CD, CC, CB, CA} <= seg3;
            else if (digit_on == 3'd4)
                {CG, CF, CE, CD, CC, CB, CA} <= seg4;
        end

        if (digit_on == 3'd4)
            digit_on <= 3'd0;
        else begin
            temp = digit_on + 3'd1;
            digit_on = temp;
        end
    end

endmodule

seven_segment_display/seven_segment_display_tb.v
`timescale 1ns / 100ps
module seven_segment_display_tb;
    reg[15:0] score = 16'd754;
    reg clk;
    wire[7:0] AN;
    wire CA, CB, CC, CD, CE, CF, CG;
    wire reset = 1'b0;

	seven_segment_display display_score(
		.clk(clk),
		.reset(reset),
		.score(score),
		.AN(AN),
		.CA(CA),
		.CB(CB),
		.CC(CC),
		.CD(CD),
		.CE(CE),
		.CF(CF),
		.CG(CG)
	);

    initial begin
        clk = 0;
        #50000000;
        $finish;
    end

    always @(clk) begin
        score <= score + 16'd1;
    end

    always
        #50000 clk = ~clk;

    always @(clk) begin
        $display("AN:%b, CA:%b, CB:%b, CC:%b, CD:%b, CE:%b, CF:%b, CG:%b", AN, CA, CB, CC, CD, CE, CF, CG);
    end

    initial begin
        $dumpfile("seven_segment_display_tb.vcd");
        $dumpvars(0, seven_segment_display_tb);
    end
endmodule

seven_segment_display/seven_segment_display_tb.vcd
$date
	Wed Apr 23 12:59:51 2025
$end
$version
	Icarus Verilog
$end
$timescale
	1ps
$end
$scope module seven_segment_display_tb $end
$var wire 1 ! reset $end
$var wire 1 " CG $end
$var wire 1 # CF $end
$var wire 1 $ CE $end
$var wire 1 % CD $end
$var wire 1 & CC $end
$var wire 1 ' CB $end
$var wire 1 ( CA $end
$var wire 8 ) AN [7:0] $end
$var reg 1 * clk $end
$var reg 16 + score [15:0] $end
$scope module display_score $end
$var wire 1 * clk $end
$var wire 1 ! reset $end
$var wire 16 , score [15:0] $end
$var wire 7 - seg4 [6:0] $end
$var wire 7 . seg3 [6:0] $end
$var wire 7 / seg2 [6:0] $end
$var wire 7 0 seg1 [6:0] $end
$var wire 7 1 seg0 [6:0] $end
$var wire 1 2 done $end
$var wire 1 3 busy $end
$var wire 4 4 bcd4 [3:0] $end
$var wire 4 5 bcd3 [3:0] $end
$var wire 4 6 bcd2 [3:0] $end
$var wire 4 7 bcd1 [3:0] $end
$var wire 4 8 bcd0 [3:0] $end
$var reg 8 9 AN [7:0] $end
$var reg 1 ( CA $end
$var reg 1 ' CB $end
$var reg 1 & CC $end
$var reg 1 % CD $end
$var reg 1 $ CE $end
$var reg 1 # CF $end
$var reg 1 " CG $end
$var reg 3 : digit_on [2:0] $end
$var reg 16 ; last_score [15:0] $end
$var reg 1 < start $end
$var reg 3 = temp [2:0] $end
$scope module bcd_0 $end
$var wire 4 > BCD [3:0] $end
$var reg 7 ? segment [6:0] $end
$upscope $end
$scope module bcd_1 $end
$var wire 4 @ BCD [3:0] $end
$var reg 7 A segment [6:0] $end
$upscope $end
$scope module bcd_2 $end
$var wire 4 B BCD [3:0] $end
$var reg 7 C segment [6:0] $end
$upscope $end
$scope module bcd_3 $end
$var wire 4 D BCD [3:0] $end
$var reg 7 E segment [6:0] $end
$upscope $end
$scope module bcd_4 $end
$var wire 4 F BCD [3:0] $end
$var reg 7 G segment [6:0] $end
$upscope $end
$scope module binary_to_BCD $end
$var wire 16 H binary_in [15:0] $end
$var wire 1 * clk $end
$var wire 1 ! reset $end
$var wire 1 < start $end
$var wire 1 I test $end
$var reg 4 J bcd0 [3:0] $end
$var reg 4 K bcd1 [3:0] $end
$var reg 4 L bcd2 [3:0] $end
$var reg 4 M bcd3 [3:0] $end
$var reg 4 N bcd4 [3:0] $end
$var reg 1 3 busy $end
$var reg 5 O counter [4:0] $end
$var reg 1 2 done $end
$var reg 36 P scratch_space [35:0] $end
$var reg 4 Q temp [3:0] $end
$upscope $end
$upscope $end
$upscope $end
$enddefinitions $end
$comment Show the parameter values. $end
$dumpall
$end
#0
$dumpvars
b0 Q
b0 P
b0 O
bx N
bx M
bx L
bx K
bx J
0I
b1011110011 H
bx G
bx F
bx E
bx D
bx C
bx B
bx A
bx @
bx ?
bx >
b0 =
0<
b0 ;
b0 :
b0 9
bx 8
bx 7
bx 6
bx 5
bx 4
03
02
bx 1
bx 0
bx /
bx .
bx -
b1011110011 ,
b1011110011 +
0*
b0 )
0(
0'
0&
0%
0$
0#
0"
0!
$end
#50000000
b1011110011 ;
1<
x"
x#
x$
x%
x&
x'
x(
b11111110 )
b11111110 9
b1011110100 +
b1011110100 ,
b1011110100 H
b1 :
b1 =
1*
#100000000
b1011110101 +
b1011110101 ,
b1011110101 H
0*
#150000000
13
b1011110101 P
b11111101 )
b11111101 9
b1011110101 ;
b1011110110 +
b1011110110 ,
b1011110110 H
b10 :
b10 =
1*
#200000000
b1011110111 +
b1011110111 ,
b1011110111 H
0*
#250000000
0<
b11111011 )
b11111011 9
b1011111000 +
b1011111000 ,
b1011111000 H
b1 O
b10111101010 P
b11 :
b11 =
1*
#300000000
b1011111001 +
b1011111001 ,
b1011111001 H
0*
#350000000
b11110111 )
b11110111 9
b1011111010 +
b1011111010 ,
b1011111010 H
b10 O
b101111010100 P
b100 :
b100 =
1*
#400000000
b1011111011 +
b1011111011 ,
b1011111011 H
0*
#450000000
b0 :
b11101111 )
b11101111 9
b1011111100 +
b1011111100 ,
b1011111100 H
b11 O
b1011110101000 P
1*
#500000000
b1011111101 +
b1011111101 ,
b1011111101 H
0*
#550000000
b11111110 )
b11111110 9
b1011111110 +
b1011111110 ,
b1011111110 H
b100 O
b10111101010000 P
b1 :
b1 =
1*
#600000000
b1011111111 +
b1011111111 ,
b1011111111 H
0*
#650000000
b11111101 )
b11111101 9
b1100000000 +
b1100000000 ,
b1100000000 H
b101 O
b101111010100000 P
b10 :
b10 =
1*
#700000000
b1100000001 +
b1100000001 ,
b1100000001 H
0*
#750000000
b11111011 )
b11111011 9
b1100000010 +
b1100000010 ,
b1100000010 H
b110 O
b1011110101000000 P
b11 :
b11 =
1*
#800000000
b1100000011 +
b1100000011 ,
b1100000011 H
0*
#850000000
b11110111 )
b11110111 9
b1100000100 +
b1100000100 ,
b1100000100 H
b111 O
b10111101010000000 P
b100 :
b100 =
1*
#900000000
b1100000101 +
b1100000101 ,
b1100000101 H
0*
#950000000
b0 :
b11101111 )
b11101111 9
b1100000110 +
b1100000110 ,
b1100000110 H
b1000 O
b101111010100000000 P
1*
#1000000000
b1100000111 +
b1100000111 ,
b1100000111 H
0*
#1050000000
b11111110 )
b11111110 9
b1100001000 +
b1100001000 ,
b1100001000 H
1I
b1001 O
b1011110101000000000 P
b1 :
b1 =
1*
#1100000000
b1100001001 +
b1100001001 ,
b1100001001 H
0*
#1150000000
b11111101 )
b11111101 9
b1100001010 +
b1100001010 ,
b1100001010 H
0I
b1010 O
b100011101010000000000 P
b1000 Q
b10 :
b10 =
1*
#1200000000
b1100001011 +
b1100001011 ,
b1100001011 H
0*
#1250000000
b11111011 )
b11111011 9
b1100001100 +
b1100001100 ,
b1100001100 H
b1011 O
b1000111010100000000000 P
b11 :
b11 =
1*
#1300000000
b1100001101 +
b1100001101 ,
b1100001101 H
0*
#1350000000
b11110111 )
b11110111 9
b1100001110 +
b1100001110 ,
b1100001110 H
1I
b1100 O
b10001110101000000000000 P
b100 :
b100 =
1*
#1400000000
b1100001111 +
b1100001111 ,
b1100001111 H
0*
#1450000000
b0 :
b11101111 )
b11101111 9
b1100010000 +
b1100010000 ,
b1100010000 H
0I
b1101 O
b100101001010000000000000 P
b1010 Q
1*
#1500000000
b1100010001 +
b1100010001 ,
b1100010001 H
0*
#1550000000
b11111110 )
b11111110 9
b1100010010 +
b1100010010 ,
b1100010010 H
1I
b1110 O
b1100010010100000000000000 P
b1100 Q
b1 :
b1 =
1*
#1600000000
b1100010011 +
b1100010011 ,
b1100010011 H
0*
#1650000000
b11111101 )
b11111101 9
b1100010100 +
b1100010100 ,
b1100010100 H
b1111 O
b1011 Q
b11011110001000000000000000 P
b10 :
b10 =
1*
#1700000000
b1100010101 +
b1100010101 ,
b1100010101 H
0*
#1750000000
b1000000 -
b1000000 G
b1000000 .
b1000000 E
b1111000 /
b1111000 C
b10010 0
b10010 A
b1111000 1
b1111000 ?
12
03
b0 4
b0 F
b0 N
b0 5
b0 D
b0 M
b111 6
b111 B
b111 L
b101 7
b101 @
b101 K
b111 8
b111 >
b111 J
b11111011 )
b11111011 9
b1100010110 +
b1100010110 ,
b1100010110 H
b10000 O
b1010 Q
b111010101110000000000000000 P
b11 :
b11 =
1*
#1800000000
b1100010111 +
b1100010111 ,
b1100010111 H
0*
#1850000000
b1100010111 ;
1<
1"
0#
0$
0%
0&
0'
0(
b11110111 )
b11110111 9
b1100011000 +
b1100011000 ,
b1100011000 H
b100 :
b100 =
1*
#1900000000
b1100011001 +
b1100011001 ,
b1100011001 H
0*
#1950000000
0I
02
13
b0 O
b1100011001 P
b0 :
b11101111 )
b11101111 9
b1100011001 ;
b1100011010 +
b1100011010 ,
b1100011010 H
1*
#2000000000
b1100011011 +
b1100011011 ,
b1100011011 H
0*
#2050000000
0<
1#
1$
1%
b11111110 )
b11111110 9
b1100011100 +
b1100011100 ,
b1100011100 H
b1 O
b11000110010 P
b1 :
b1 =
1*
#2100000000
b1100011101 +
b1100011101 ,
b1100011101 H
0*
#2150000000
0"
0#
0%
1'
b11111101 )
b11111101 9
b1100011110 +
b1100011110 ,
b1100011110 H
b10 O
b110001100100 P
b10 :
b10 =
1*
#2200000000
b1100011111 +
b1100011111 ,
b1100011111 H
0*
#2250000000
1"
1#
1%
0'
b11111011 )
b11111011 9
b1100100000 +
b1100100000 ,
b1100100000 H
b11 O
b1100011001000 P
b11 :
b11 =
1*
#2300000000
b1100100001 +
b1100100001 ,
b1100100001 H
0*
#2350000000
0#
0$
0%
b11110111 )
b11110111 9
b1100100010 +
b1100100010 ,
b1100100010 H
b100 O
b11000110010000 P
b100 :
b100 =
1*
#2400000000
b1100100011 +
b1100100011 ,
b1100100011 H
0*
#2450000000
b0 :
b11101111 )
b11101111 9
b1100100100 +
b1100100100 ,
b1100100100 H
b101 O
b110001100100000 P
1*
#2500000000
b1100100101 +
b1100100101 ,
b1100100101 H
0*
#2550000000
1#
1$
1%
b11111110 )
b11111110 9
b1100100110 +
b1100100110 ,
b1100100110 H
b110 O
b1100011001000000 P
b1 :
b1 =
1*
#2600000000
b1100100111 +
b1100100111 ,
b1100100111 H
0*
#2650000000
0"
0#
0%
1'
b11111101 )
b11111101 9
b1100101000 +
b1100101000 ,
b1100101000 H
b111 O
b11000110010000000 P
b10 :
b10 =
1*
#2700000000
b1100101001 +
b1100101001 ,
b1100101001 H
0*
#2750000000
1"
1#
1%
0'
b11111011 )
b11111011 9
b1100101010 +
b1100101010 ,
b1100101010 H
b1000 O
b110001100100000000 P
b11 :
b11 =
1*
#2800000000
b1100101011 +
b1100101011 ,
b1100101011 H
0*
#2850000000
0#
0$
0%
b11110111 )
b11110111 9
b1100101100 +
b1100101100 ,
b1100101100 H
1I
b1001 O
b1100011001000000000 P
b100 :
b100 =
1*
#2900000000
b1100101101 +
b1100101101 ,
b1100101101 H
0*
#2950000000
b0 :
b11101111 )
b11101111 9
b1100101110 +
b1100101110 ,
b1100101110 H
0I
b1010 O
b100100110010000000000 P
b1001 Q
1*
#3000000000
b1100101111 +
b1100101111 ,
b1100101111 H
0*
#3050000000
1#
1$
1%
b11111110 )
b11111110 9
b1100110000 +
b1100110000 ,
b1100110000 H
b1011 O
b1001001100100000000000 P
b1 :
b1 =
1*
#3100000000
b1100110001 +
b1100110001 ,
b1100110001 H
0*
#3150000000
0"
0#
0%
1'
b11111101 )
b11111101 9
b1100110010 +
b1100110010 ,
b1100110010 H
1I
b1100 O
b10010011001000000000000 P
b10 :
b10 =
1*
#3200000000
b1100110011 +
b1100110011 ,
b1100110011 H
0*
#3250000000
1"
1#
1%
0'
b11111011 )
b11111011 9
b1100110100 +
b1100110100 ,
b1100110100 H
b1101 O
b100110010010000000000000 P
b1100 Q
b11 :
b11 =
1*
#3300000000
b1100110101 +
b1100110101 ,
b1100110101 H
0*
#3350000000
0#
0$
0%
b11110111 )
b11110111 9
b1100110110 +
b1100110110 ,
b1100110110 H
b1110 O
b1100110000100000000000000 P
b100 :
b100 =
1*
#3400000000
b1100110111 +
b1100110111 ,
b1100110111 H
0*
#3450000000
b0 :
b11101111 )
b11101111 9
b1100111000 +
b1100111000 ,
b1100111000 H
b1111 O
b11100101101000000000000000 P
b1100 Q
1*
#3500000000
b1100111001 +
b1100111001 ,
b1100111001 H
0*
#3550000000
b10000 0
b10000 A
b110000 1
b110000 ?
12
03
b1001 7
b1001 @
b1001 K
b11 8
b11 >
b11 J
1#
1$
1%
b11111110 )
b11111110 9
b1100111010 +
b1100111010 ,
b1100111010 H
0I
b10000 O
b111100100110000000000000000 P
b1100 Q
b1 :
b1 =
1*
#3600000000
b1100111011 +
b1100111011 ,
b1100111011 H
0*
#3650000000
b1100111011 ;
1<
0"
0#
0%
b11111101 )
b11111101 9
b1100111100 +
b1100111100 ,
b1100111100 H
b10 :
b10 =
1*
#3700000000
b1100111101 +
b1100111101 ,
b1100111101 H
0*
#3750000000
02
13
b0 O
b1100111101 P
1"
1#
1%
b11111011 )
b11111011 9
b1100111101 ;
b1100111110 +
b1100111110 ,
b1100111110 H
b11 :
b11 =
1*
#3800000000
b1100111111 +
b1100111111 ,
b1100111111 H
0*
#3850000000
0<
0#
0$
0%
b11110111 )
b11110111 9
b1101000000 +
b1101000000 ,
b1101000000 H
b1 O
b11001111010 P
b100 :
b100 =
1*
#3900000000
b1101000001 +
b1101000001 ,
b1101000001 H
0*
#3950000000
b0 :
b11101111 )
b11101111 9
b1101000010 +
b1101000010 ,
b1101000010 H
b10 O
b110011110100 P
1*
#4000000000
b1101000011 +
b1101000011 ,
b1101000011 H
0*
#4050000000
0"
1#
1$
b11111110 )
b11111110 9
b1101000100 +
b1101000100 ,
b1101000100 H
b11 O
b1100111101000 P
b1 :
b1 =
1*
#4100000000
b1101000101 +
b1101000101 ,
b1101000101 H
0*
#4150000000
0#
b11111101 )
b11111101 9
b1101000110 +
b1101000110 ,
b1101000110 H
b100 O
b11001111010000 P
b10 :
b10 =
1*
#4200000000
b1101000111 +
b1101000111 ,
b1101000111 H
0*
#4250000000
1"
1#
1%
b11111011 )
b11111011 9
b1101001000 +
b1101001000 ,
b1101001000 H
b101 O
b110011110100000 P
b11 :
b11 =
1*
#4300000000
b1101001001 +
b1101001001 ,
b1101001001 H
0*
#4350000000
0#
0$
0%
b11110111 )
b11110111 9
b1101001010 +
b1101001010 ,
b1101001010 H
b110 O
b1100111101000000 P
b100 :
b100 =
1*
#4400000000
b1101001011 +
b1101001011 ,
b1101001011 H
0*
#4450000000
b0 :
b11101111 )
b11101111 9
b1101001100 +
b1101001100 ,
b1101001100 H
b111 O
b11001111010000000 P
1*
#4500000000
b1101001101 +
b1101001101 ,
b1101001101 H
0*
#4550000000
0"
1#
1$
b11111110 )
b11111110 9
b1101001110 +
b1101001110 ,
b1101001110 H
b1000 O
b110011110100000000 P
b1 :
b1 =
1*
#4600000000
b1101001111 +
b1101001111 ,
b1101001111 H
0*
#4650000000
0#
b11111101 )
b11111101 9
b1101010000 +
b1101010000 ,
b1101010000 H
1I
b1001 O
b1100111101000000000 P
b10 :
b10 =
1*
#4700000000
b1101010001 +
b1101010001 ,
b1101010001 H
0*
#4750000000
1"
1#
1%
b11111011 )
b11111011 9
b1101010010 +
b1101010010 ,
b1101010010 H
0I
b1010 O
b100101111010000000000 P
b1001 Q
b11 :
b11 =
1*
#4800000000
b1101010011 +
b1101010011 ,
b1101010011 H
0*
#4850000000
0#
0$
0%
b11110111 )
b11110111 9
b1101010100 +
b1101010100 ,
b1101010100 H
1I
b1011 O
b1001011110100000000000 P
b100 :
b100 =
1*
#4900000000
b1101010101 +
b1101010101 ,
b1101010101 H
0*
#4950000000
b0 :
b11101111 )
b11101111 9
b1101010110 +
b1101010110 ,
b1101010110 H
0I
b1100 O
b10100011101000000000000 P
b1000 Q
1*
#5000000000
b1101010111 +
b1101010111 ,
b1101010111 H
0*
#5050000000
0"
1#
1$
b11111110 )
b11111110 9
b1101011000 +
b1101011000 ,
b1101011000 H
b1101 O
b1000000111010000000000000 P
b1 :
b1 =
1*
#5100000000
b1101011001 +
b1101011001 ,
b1101011001 H
0*
#5150000000
0#
b11111101 )
b11111101 9
b1101011010 +
b1101011010 ,
b1101011010 H
1I
b1110 O
b10000001110100000000000000 P
b10 :
b10 =
1*
#5200000000
b1101011011 +
b1101011011 ,
b1101011011 H
0*
#5250000000
1"
1#
1%
b11111011 )
b11111011 9
b1101011100 +
b1101011100 ,
b1101011100 H
0I
b1111 O
b100000101001000000000000000 P
b1010 Q
b11 :
b11 =
1*
#5300000000
b1101011101 +
b1101011101 ,
b1101011101 H
0*
#5350000000
b0 /
b0 C
b100100 0
b100100 A
b10000 1
b10000 ?
12
03
b1000 6
b1000 B
b1000 L
b10 7
b10 @
b10 K
b1001 8
b1001 >
b1001 J
0#
0$
0%
b11110111 )
b11110111 9
b1101011110 +
b1101011110 ,
b1101011110 H
1I
b10000 O
b1000001010010000000000000000 P
b100 :
b100 =
1*
#5400000000
b1101011111 +
b1101011111 ,
b1101011111 H
0*
#5450000000
b1101011111 ;
1<
b0 :
b11101111 )
b11101111 9
b1101100000 +
b1101100000 ,
b1101100000 H
1*
#5500000000
b1101100001 +
b1101100001 ,
b1101100001 H
0*
#5550000000
0I
02
13
b0 O
b1101100001 P
0"
1$
b11111110 )
b11111110 9
b1101100001 ;
b1101100010 +
b1101100010 ,
b1101100010 H
b1 :
b1 =
1*
#5600000000
b1101100011 +
b1101100011 ,
b1101100011 H
0*
#5650000000
0<
1#
0$
1&
b11111101 )
b11111101 9
b1101100100 +
b1101100100 ,
b1101100100 H
b1 O
b11011000010 P
b10 :
b10 =
1*
#5700000000
b1101100101 +
b1101100101 ,
b1101100101 H
0*
#5750000000
0#
0&
b11111011 )
b11111011 9
b1101100110 +
b1101100110 ,
b1101100110 H
b10 O
b110110000100 P
b11 :
b11 =
1*
#5800000000
b1101100111 +
b1101100111 ,
b1101100111 H
0*
#5850000000
1"
b11110111 )
b11110111 9
b1101101000 +
b1101101000 ,
b1101101000 H
b11 O
b1101100001000 P
b100 :
b100 =
1*
#5900000000
b1101101001 +
b1101101001 ,
b1101101001 H
0*
#5950000000
b0 :
b11101111 )
b11101111 9
b1101101010 +
b1101101010 ,
b1101101010 H
b100 O
b11011000010000 P
1*
#6000000000
b1101101011 +
b1101101011 ,
b1101101011 H
0*
#6050000000
0"
1$
b11111110 )
b11111110 9
b1101101100 +
b1101101100 ,
b1101101100 H
b101 O
b110110000100000 P
b1 :
b1 =
1*
#6100000000
b1101101101 +
b1101101101 ,
b1101101101 H
0*
#6150000000
1#
0$
1&
b11111101 )
b11111101 9
b1101101110 +
b1101101110 ,
b1101101110 H
b110 O
b1101100001000000 P
b10 :
b10 =
1*
#6200000000
b1101101111 +
b1101101111 ,
b1101101111 H
0*
#6250000000
0#
0&
b11111011 )
b11111011 9
b1101110000 +
b1101110000 ,
b1101110000 H
b111 O
b11011000010000000 P
b11 :
b11 =
1*
#6300000000
b1101110001 +
b1101110001 ,
b1101110001 H
0*
#6350000000
1"
b11110111 )
b11110111 9
b1101110010 +
b1101110010 ,
b1101110010 H
b1000 O
b110110000100000000 P
b100 :
b100 =
1*
#6400000000
b1101110011 +
b1101110011 ,
b1101110011 H
0*
#6450000000
b0 :
b11101111 )
b11101111 9
b1101110100 +
b1101110100 ,
b1101110100 H
1I
b1001 O
b1101100001000000000 P
1*
#6500000000
b1101110101 +
b1101110101 ,
b1101110101 H
0*
#6550000000
0"
1$
b11111110 )
b11111110 9
b1101110110 +
b1101110110 ,
b1101110110 H
0I
b1010 O
b100111000010000000000 P
b1001 Q
b1 :
b1 =
1*
#6600000000
b1101110111 +
b1101110111 ,
b1101110111 H
0*
#6650000000
1#
0$
1&
b11111101 )
b11111101 9
b1101111000 +
b1101111000 ,
b1101111000 H
1I
b1011 O
b1001110000100000000000 P
b10 :
b10 =
1*
#6700000000
b1101111001 +
b1101111001 ,
b1101111001 H
0*
#6750000000
0#
0&
b11111011 )
b11111011 9
b1101111010 +
b1101111010 ,
b1101111010 H
0I
b1100 O
b10101000001000000000000 P
b1010 Q
b11 :
b11 =
1*
#6800000000
b1101111011 +
b1101111011 ,
b1101111011 H
0*
#6850000000
1"
b11110111 )
b11110111 9
b1101111100 +
b1101111100 ,
b1101111100 H
1I
b1101 O
b1000010000010000000000000 P
b1000 Q
b100 :
b100 =
1*
#6900000000
b1101111101 +
b1101111101 ,
b1101111101 H
0*
#6950000000
b0 :
b11101111 )
b11101111 9
b1101111110 +
b1101111110 ,
b1101111110 H
b1110 O
b10000101100100000000000000 P
b1011 Q
1*
#7000000000
b1101111111 +
b1101111111 ,
b1101111111 H
0*
#7050000000
0"
1$
b11111110 )
b11111110 9
b1110000000 +
b1110000000 ,
b1110000000 H
0I
b1111 O
b100001100101000000000000000 P
b1001 Q
b1 :
b1 =
1*
#7100000000
b1110000001 +
b1110000001 ,
b1110000001 H
0*
#7150000000
b10 0
b10 A
b10010 1
b10010 ?
12
03
b110 7
b110 @
b110 K
b101 8
b101 >
b101 J
1#
0$
1&
b11111101 )
b11111101 9
b1110000010 +
b1110000010 ,
b1110000010 H
1I
b10000 O
b1000011001010000000000000000 P
b10 :
b10 =
1*
#7200000000
b1110000011 +
b1110000011 ,
b1110000011 H
0*
#7250000000
b1110000011 ;
1<
0#
0&
b11111011 )
b11111011 9
b1110000100 +
b1110000100 ,
b1110000100 H
b11 :
b11 =
1*
#7300000000
b1110000101 +
b1110000101 ,
b1110000101 H
0*
#7350000000
0I
02
13
b0 O
b1110000101 P
1"
b11110111 )
b11110111 9
b1110000101 ;
b1110000110 +
b1110000110 ,
b1110000110 H
b100 :
b100 =
1*
#7400000000
b1110000111 +
b1110000111 ,
b1110000111 H
0*
#7450000000
0<
b0 :
b11101111 )
b11101111 9
b1110001000 +
b1110001000 ,
b1110001000 H
b1 O
b11100001010 P
1*
#7500000000
b1110001001 +
b1110001001 ,
b1110001001 H
0*
#7550000000
0"
1$
1'
b11111110 )
b11111110 9
b1110001010 +
b1110001010 ,
b1110001010 H
b10 O
b111000010100 P
b1 :
b1 =
1*
#7600000000
b1110001011 +
b1110001011 ,
b1110001011 H
0*
#7650000000
0$
b11111101 )
b11111101 9
b1110001100 +
b1110001100 ,
b1110001100 H
b11 O
b1110000101000 P
b10 :
b10 =
1*
#7700000000
b1110001101 +
b1110001101 ,
b1110001101 H
0*
#7750000000
0'
b11111011 )
b11111011 9
b1110001110 +
b1110001110 ,
b1110001110 H
b100 O
b11100001010000 P
b11 :
b11 =
1*
#7800000000
b1110001111 +
b1110001111 ,
b1110001111 H
0*
#7850000000
1"
b11110111 )
b11110111 9
b1110010000 +
b1110010000 ,
b1110010000 H
b101 O
b111000010100000 P
b100 :
b100 =
1*
#7900000000
b1110010001 +
b1110010001 ,
b1110010001 H
0*
#7950000000
b0 :
b11101111 )
b11101111 9
b1110010010 +
b1110010010 ,
b1110010010 H
b110 O
b1110000101000000 P
1*
#8000000000
b1110010011 +
b1110010011 ,
b1110010011 H
0*
#8050000000
0"
1$
1'
b11111110 )
b11111110 9
b1110010100 +
b1110010100 ,
b1110010100 H
b111 O
b11100001010000000 P
b1 :
b1 =
1*
#8100000000
b1110010101 +
b1110010101 ,
b1110010101 H
0*
#8150000000
0$
b11111101 )
b11111101 9
b1110010110 +
b1110010110 ,
b1110010110 H
b1000 O
b111000010100000000 P
b10 :
b10 =
1*
#8200000000
b1110010111 +
b1110010111 ,
b1110010111 H
0*
#8250000000
0'
b11111011 )
b11111011 9
b1110011000 +
b1110011000 ,
b1110011000 H
1I
b1001 O
b1110000101000000000 P
b11 :
b11 =
1*
#8300000000
b1110011001 +
b1110011001 ,
b1110011001 H
0*
#8350000000
1"
b11110111 )
b11110111 9
b1110011010 +
b1110011010 ,
b1110011010 H
0I
b1010 O
b101000001010000000000 P
b1010 Q
b100 :
b100 =
1*
#8400000000
b1110011011 +
b1110011011 ,
b1110011011 H
0*
#8450000000
b0 :
b11101111 )
b11101111 9
b1110011100 +
b1110011100 ,
b1110011100 H
1I
b1011 O
b1010000010100000000000 P
1*
#8500000000
b1110011101 +
b1110011101 ,
b1110011101 H
0*
#8550000000
0"
1$
1'
b11111110 )
b11111110 9
b1110011110 +
b1110011110 ,
b1110011110 H
b1100 O
b10101100101000000000000 P
b1011 Q
b1 :
b1 =
1*
#8600000000
b1110011111 +
b1110011111 ,
b1110011111 H
0*
#8650000000
0$
b11111101 )
b11111101 9
b1110100000 +
b1110100000 ,
b1110100000 H
0I
b1101 O
b1000100101010000000000000 P
b1000 Q
b10 :
b10 =
1*
#8700000000
b1110100001 +
b1110100001 ,
b1110100001 H
0*
